advai/__init__.py
advai/main.py
advai_versus-2023.0.1a1.dist-info/LICENSE
advai_versus-2023.0.1a1.dist-info/METADATA
advai_versus-2023.0.1a1.dist-info/WHEEL
advai_versus-2023.0.1a1.dist-info/top_level.txt
advai_versus-2023.0.1a1.dist-info/RECORD
