Metadata-Version: 2.1
Name: advai-versus
Version: 2023.0.1a1
Summary: A simple namespace project.
Author-email: "Advai Ltd." <support@advai.co.uk>
Project-URL: homepage, https://www.advai.co.uk
Project-URL: repository, https://github.com/Advai-Ltd/advai-versus
Keywords: Advai
Requires-Python: >=3.11
License-File: LICENSE
